pytest_pings/__init__.py
pytest_pings/plugin.py
pytest_pings-0.1.0.dist-info/LICENSE
pytest_pings-0.1.0.dist-info/METADATA
pytest_pings-0.1.0.dist-info/WHEEL
pytest_pings-0.1.0.dist-info/entry_points.txt
pytest_pings-0.1.0.dist-info/top_level.txt
pytest_pings-0.1.0.dist-info/RECORD
